{"results":[{"properties":[{"key":"y_wgs84","value":"52.266624"},{"key":"x_wgs84","value":"20.977741"},{"key":"adres","value":""},{"key":"data_wyk_pom","value":"null"},{"key":"gatunek1","value":"**"},{"key":"gatunek","value":"** nieokreślony **"},{"key":"wiek_w_dni","value":"0"},{"key":"jednostka","value":"Dzielnica Żoliborz"},{"key":"rank","value":"0.0573088"},{"key":"_full_count","value":"964"},{"key":"_id","value":"21442"},{"key":"dzielnica","value":""},{"key":"stan_zdrowia","value":""},{"key":"miasto","value":"Warszawa"},{"key":"lokalizacja","value":""},{"key":"numer_inw","value":"K35485"},{"key":"y","value":"5792564.99090909"},{"key":"x","value":"7498480.52251748"}]},{"properties":[{"key":"y_wgs84","value":"52.264613"},{"key":"x_wgs84","value":"20.983189"},{"key":"adres","value":"ul. WIENIAWSKIEGO H"},{"key":"data_wyk_pom","value":"18991230"},{"key":"gatunek1","value":"Taxus baccata 'Repandens'"},{"key":"gatunek","value":"cis pospolity \"Repandens\""},{"key":"wiek_w_dni","value":"0"},{"key":"jednostka","value":"Dzielnica Żoliborz"},{"key":"rank","value":"0.0706241"},{"key":"_full_count","value":"964"},{"key":"_id","value":"6503"},{"key":"dzielnica","value":"Żoliborz"},{"key":"stan_zdrowia","value":"dobry"},{"key":"miasto","value":"Warszawa"},{"key":"lokalizacja","value":"Ulica bez nazwy"},{"key":"numer_inw","value":"K13231"},{"key":"y","value":"5792341.07314685"},{"key":"x","value":"7498852.36839161"}]},{"properties":[{"key":"y_wgs84","value":"52.262554"},{"key":"x_wgs84","value":"20.989211"},{"key":"adres","value":"ul. LISA-KULI L"},{"key":"data_wyk_pom","value":"18991230"},{"key":"gatunek1","value":"Rosa  sp."},{"key":"gatunek","value":"róża  sp."},{"key":"wiek_w_dni","value":"0"},{"key":"jednostka","value":"Dzielnica Żoliborz"},{"key":"rank","value":"0.0706241"},{"key":"_full_count","value":"964"},{"key":"_id","value":"6351"},{"key":"dzielnica","value":"Żoliborz"},{"key":"stan_zdrowia","value":"dobry"},{"key":"miasto","value":"Warszawa"},{"key":"lokalizacja","value":"Ulica bez nazwy"},{"key":"numer_inw","value":"K13182"},{"key":"y","value":"5792111.95216783"},{"key":"x","value":"7499263.45398601"}]},{"properties":[{"key":"y_wgs84","value":"52.264852"},{"key":"x_wgs84","value":"20.983074"},{"key":"adres","value":"ul. WIENIAWSKIEGO H"},{"key":"data_wyk_pom","value":"18991230"},{"key":"gatunek1","value":"Juniperus  sp."},{"key":"gatunek","value":"jałowiec  sp."},{"key":"wiek_w_dni","value":"0"},{"key":"jednostka","value":"Dzielnica Żoliborz"},{"key":"rank","value":"0.0706241"},{"key":"_full_count","value":"964"},{"key":"_id","value":"6505"},{"key":"dzielnica","value":"Żoliborz"},{"key":"stan_zdrowia","value":"średni"},{"key":"miasto","value":"Warszawa"},{"key":"lokalizacja","value":"Ulica bez nazwy"},{"key":"numer_inw","value":"K13233"},{"key":"y","value":"5792367.65006993"},{"key":"x","value":"7498844.50041958"}]},{"properties":[{"key":"y_wgs84","value":"52.264864"},{"key":"x_wgs84","value":"20.983068"},{"key":"adres","value":"ul. WIENIAWSKIEGO H"},{"key":"data_wyk_pom","value":"18991230"},{"key":"gatunek1","value":"Juniperus  sp."},{"key":"gatunek","value":"jałowiec  sp."},{"key":"wiek_w_dni","value":"0"},{"key":"jednostka","value":"Dzielnica Żoliborz"},{"key":"rank","value":"0.0706241"},{"key":"_full_count","value":"964"},{"key":"_id","value":"6506"},{"key":"dzielnica","value":"Żoliborz"},{"key":"stan_zdrowia","value":"średni"},{"key":"miasto","value":"Warszawa"},{"key":"lokalizacja","value":"Ulica bez nazwy"},{"key":"numer_inw","value":"K13234"},{"key":"y","value":"5792369.01972028"},{"key":"x","value":"7498844.08923077"}]},{"properties":[{"key":"y_wgs84","value":"52.264905"},{"key":"x_wgs84","value":"20.983062"},{"key":"adres","value":"ul. WIENIAWSKIEGO H"},{"key":"data_wyk_pom","value":"18991230"},{"key":"gatunek1","value":"Juniperus  sp."},{"key":"gatunek","value":"jałowiec  sp."},{"key":"wiek_w_dni","value":"0"},{"key":"jednostka","value":"Dzielnica Żoliborz"},{"key":"rank","value":"0.0706241"},{"key":"_full_count","value":"964"},{"key":"_id","value":"6507"},{"key":"dzielnica","value":"Żoliborz"},{"key":"stan_zdrowia","value":"dobry"},{"key":"miasto","value":"Warszawa"},{"key":"lokalizacja","value":"Ulica bez nazwy"},{"key":"numer_inw","value":"K13235"},{"key":"y","value":"5792373.54041958"},{"key":"x","value":"7498843.7241958"}]},{"properties":[{"key":"y_wgs84","value":"52.267602"},{"key":"x_wgs84","value":"20.987161"},{"key":"adres","value":"ul. MICKIEWICZA A"},{"key":"data_wyk_pom","value":"18991230"},{"key":"gatunek1","value":"Symphoricarpos albus"},{"key":"gatunek","value":"śnieguliczka biała"},{"key":"wiek_w_dni","value":"0"},{"key":"jednostka","value":"Dzielnica Żoliborz"},{"key":"rank","value":"0.0706241"},{"key":"_full_count","value":"964"},{"key":"_id","value":"6319"},{"key":"dzielnica","value":"Żoliborz"},{"key":"stan_zdrowia","value":"dobry"},{"key":"miasto","value":"Warszawa"},{"key":"lokalizacja","value":"Ulica bez nazwy"},{"key":"numer_inw","value":"K12656"},{"key":"y","value":"5792673.60405594"},{"key":"x","value":"7499123.60811189"}]},{"properties":[{"key":"y_wgs84","value":"52.265011"},{"key":"x_wgs84","value":"20.983075"},{"key":"adres","value":"ul. WIENIAWSKIEGO H"},{"key":"data_wyk_pom","value":"18991230"},{"key":"gatunek1","value":"Ligustrum vulgare"},{"key":"gatunek","value":"ligustr pospolity"},{"key":"wiek_w_dni","value":"0"},{"key":"jednostka","value":"Dzielnica Żoliborz"},{"key":"rank","value":"0.0706241"},{"key":"_full_count","value":"964"},{"key":"_id","value":"6509"},{"key":"dzielnica","value":"Żoliborz"},{"key":"stan_zdrowia","value":"średni"},{"key":"miasto","value":"Warszawa"},{"key":"lokalizacja","value":"Ulica bez nazwy"},{"key":"numer_inw","value":"K13237"},{"key":"y","value":"5792385.36685315"},{"key":"x","value":"7498844.5965035"}]},{"properties":[{"key":"y_wgs84","value":"52.265412"},{"key":"x_wgs84","value":"20.982854"},{"key":"adres","value":"ul. WIENIAWSKIEGO H"},{"key":"data_wyk_pom","value":"18991230"},{"key":"gatunek1","value":"Thuja occidentalis"},{"key":"gatunek","value":"żywotnik zachodni"},{"key":"wiek_w_dni","value":"0"},{"key":"jednostka","value":"Dzielnica Żoliborz"},{"key":"rank","value":"0.0706241"},{"key":"_full_count","value":"964"},{"key":"_id","value":"6510"},{"key":"dzielnica","value":"Żoliborz"},{"key":"stan_zdrowia","value":"dobry"},{"key":"miasto","value":"Warszawa"},{"key":"lokalizacja","value":"Ulica bez nazwy"},{"key":"numer_inw","value":"K13238"},{"key":"y","value":"5792430.02643357"},{"key":"x","value":"7498829.50097902"}]},{"properties":[{"key":"y_wgs84","value":"52.265543"},{"key":"x_wgs84","value":"20.982835"},{"key":"adres","value":"ul. WIENIAWSKIEGO H"},{"key":"data_wyk_pom","value":"18991230"},{"key":"gatunek1","value":"Rosa  sp."},{"key":"gatunek","value":"róża  sp."},{"key":"wiek_w_dni","value":"0"},{"key":"jednostka","value":"Dzielnica Żoliborz"},{"key":"rank","value":"0.0706241"},{"key":"_full_count","value":"964"},{"key":"_id","value":"6511"},{"key":"dzielnica","value":"Żoliborz"},{"key":"stan_zdrowia","value":"średni"},{"key":"miasto","value":"Warszawa"},{"key":"lokalizacja","value":"Ulica bez nazwy"},{"key":"numer_inw","value":"K13239"},{"key":"y","value":"5792444.59244755"},{"key":"x","value":"7498828.2227972"}]},{"properties":[{"key":"y_wgs84","value":"52.265577"},{"key":"x_wgs84","value":"20.982828"},{"key":"adres","value":"ul. WIENIAWSKIEGO H"},{"key":"data_wyk_pom","value":"18991230"},{"key":"gatunek1","value":"Rosa  sp."},{"key":"gatunek","value":"róża  sp."},{"key":"wiek_w_dni","value":"0"},{"key":"jednostka","value":"Dzielnica Żoliborz"},{"key":"rank","value":"0.0706241"},{"key":"_full_count","value":"964"},{"key":"_id","value":"6512"},{"key":"dzielnica","value":"Żoliborz"},{"key":"stan_zdrowia","value":"dobry"},{"key":"miasto","value":"Warszawa"},{"key":"lokalizacja","value":"Ulica bez nazwy"},{"key":"numer_inw","value":"K13240"},{"key":"y","value":"5792448.3820979"},{"key":"x","value":"7498827.72013986"}]},{"properties":[{"key":"y_wgs84","value":"52.267733"},{"key":"x_wgs84","value":"20.979121"},{"key":"adres","value":"ul. PRÓCHNIKA A"},{"key":"data_wyk_pom","value":"18991230"},{"key":"gatunek1","value":"Syringa vulgaris"},{"key":"gatunek","value":"lilak pospolity"},{"key":"wiek_w_dni","value":"0"},{"key":"jednostka","value":"Dzielnica Żoliborz"},{"key":"rank","value":"0.0706241"},{"key":"_full_count","value":"964"},{"key":"_id","value":"6513"},{"key":"dzielnica","value":"Żoliborz"},{"key":"stan_zdrowia","value":"dobry"},{"key":"miasto","value":"Warszawa"},{"key":"lokalizacja","value":"Ulica bez nazwy"},{"key":"numer_inw","value":"K13241"},{"key":"y","value":"5792688.29678322"},{"key":"x","value":"7498574.74125874"}]},{"properties":[{"key":"y_wgs84","value":"52.267735"},{"key":"x_wgs84","value":"20.979155"},{"key":"adres","value":"ul. PRÓCHNIKA A"},{"key":"data_wyk_pom","value":"18991230"},{"key":"gatunek1","value":"Syringa vulgaris"},{"key":"gatunek","value":"lilak pospolity"},{"key":"wiek_w_dni","value":"0"},{"key":"jednostka","value":"Dzielnica Żoliborz"},{"key":"rank","value":"0.0706241"},{"key":"_full_count","value":"964"},{"key":"_id","value":"6514"},{"key":"dzielnica","value":"Żoliborz"},{"key":"stan_zdrowia","value":"dobry"},{"key":"miasto","value":"Warszawa"},{"key":"lokalizacja","value":"Ulica bez nazwy"},{"key":"numer_inw","value":"K13242"},{"key":"y","value":"5792688.57006993"},{"key":"x","value":"7498577.0758042"}]},{"properties":[{"key":"y_wgs84","value":"52.267755"},{"key":"x_wgs84","value":"20.979189"},{"key":"adres","value":"ul. PRÓCHNIKA A"},{"key":"data_wyk_pom","value":"18991230"},{"key":"gatunek1","value":"Syringa vulgaris"},{"key":"gatunek","value":"lilak pospolity"},{"key":"wiek_w_dni","value":"0"},{"key":"jednostka","value":"Dzielnica Żoliborz"},{"key":"rank","value":"0.0706241"},{"key":"_full_count","value":"964"},{"key":"_id","value":"6515"},{"key":"dzielnica","value":"Żoliborz"},{"key":"stan_zdrowia","value":"dobry"},{"key":"miasto","value":"Warszawa"},{"key":"lokalizacja","value":"Ulica bez nazwy"},{"key":"numer_inw","value":"K13243"},{"key":"y","value":"5792690.80699301"},{"key":"x","value":"7498579.36489511"}]},{"properties":[{"key":"y_wgs84","value":"52.268695"},{"key":"x_wgs84","value":"20.98267"},{"key":"adres","value":"ul. FILARECKA"},{"key":"data_wyk_pom","value":"18991230"},{"key":"gatunek1","value":"Thuja occidentalis"},{"key":"gatunek","value":"żywotnik zachodni"},{"key":"wiek_w_dni","value":"0"},{"key":"jednostka","value":"Dzielnica Żoliborz"},{"key":"rank","value":"0.0706241"},{"key":"_full_count","value":"964"},{"key":"_id","value":"6516"},{"key":"dzielnica","value":"Żoliborz"},{"key":"stan_zdrowia","value":"dobry"},{"key":"miasto","value":"Warszawa"},{"key":"lokalizacja","value":"Ulica bez nazwy"},{"key":"numer_inw","value":"K13244"},{"key":"y","value":"5792795.25510489"},{"key":"x","value":"7498817.04573427"}]},{"properties":[{"key":"y_wgs84","value":"52.273945"},{"key":"x_wgs84","value":"20.976869"},{"key":"adres","value":"ul. PASKA JC"},{"key":"data_wyk_pom","value":"18991230"},{"key":"gatunek1","value":"Ilex  sp."},{"key":"gatunek","value":"ostrokrzew  sp."},{"key":"wiek_w_dni","value":"0"},{"key":"jednostka","value":"Dzielnica Żoliborz"},{"key":"rank","value":"0.0706241"},{"key":"_full_count","value":"964"},{"key":"_id","value":"7006"},{"key":"dzielnica","value":"Żoliborz"},{"key":"stan_zdrowia","value":"dobry"},{"key":"miasto","value":"Warszawa"},{"key":"lokalizacja","value":"Ulica bez nazwy"},{"key":"numer_inw","value":"K12307"},{"key":"y","value":"5793379.51496504"},{"key":"x","value":"7498421.25454545"}]},{"properties":[{"key":"y_wgs84","value":"52.273932"},{"key":"x_wgs84","value":"20.976786"},{"key":"adres","value":"ul. PASKA JC"},{"key":"data_wyk_pom","value":"18991230"},{"key":"gatunek1","value":"Ilex  sp."},{"key":"gatunek","value":"ostrokrzew  sp."},{"key":"wiek_w_dni","value":"0"},{"key":"jednostka","value":"Dzielnica Żoliborz"},{"key":"rank","value":"0.0706241"},{"key":"_full_count","value":"964"},{"key":"_id","value":"7007"},{"key":"dzielnica","value":"Żoliborz"},{"key":"stan_zdrowia","value":"dobry"},{"key":"miasto","value":"Warszawa"},{"key":"lokalizacja","value":"Ulica bez nazwy"},{"key":"numer_inw","value":"K12308"},{"key":"y","value":"5793378.10153846"},{"key":"x","value":"7498415.57902098"}]},{"properties":[{"key":"y_wgs84","value":"52.275682"},{"key":"x_wgs84","value":"20.972497"},{"key":"adres","value":"ul. GDAŃSKA"},{"key":"data_wyk_pom","value":"18991230"},{"key":"gatunek1","value":"Prunus cerasifera"},{"key":"gatunek","value":"śliwa ałycza"},{"key":"wiek_w_dni","value":"0"},{"key":"jednostka","value":"Dzielnica Żoliborz"},{"key":"rank","value":"0.0706241"},{"key":"_full_count","value":"964"},{"key":"_id","value":"7008"},{"key":"dzielnica","value":"Żoliborz"},{"key":"stan_zdrowia","value":"dobry"},{"key":"miasto","value":"Warszawa"},{"key":"lokalizacja","value":"Ulica bez nazwy"},{"key":"numer_inw","value":"K12309"},{"key":"y","value":"5793572.90517483"},{"key":"x","value":"7498122.92671329"}]},{"properties":[{"key":"y_wgs84","value":"52.274706"},{"key":"x_wgs84","value":"20.968692"},{"key":"adres","value":"al. ARMII KRAJOWEJ"},{"key":"data_wyk_pom","value":"18991230"},{"key":"gatunek1","value":"Prunus cerasifera"},{"key":"gatunek","value":"śliwa ałycza"},{"key":"wiek_w_dni","value":"0"},{"key":"jednostka","value":"Dzielnica Żoliborz"},{"key":"rank","value":"0.0706241"},{"key":"_full_count","value":"964"},{"key":"_id","value":"7009"},{"key":"dzielnica","value":"Żoliborz"},{"key":"stan_zdrowia","value":"dobry"},{"key":"miasto","value":"Warszawa"},{"key":"lokalizacja","value":"Ulica bez nazwy"},{"key":"numer_inw","value":"K12816"},{"key":"y","value":"5793464.40839161"},{"key":"x","value":"7497863.16237762"}]},{"properties":[{"key":"y_wgs84","value":"52.274734"},{"key":"x_wgs84","value":"20.968759"},{"key":"adres","value":"al. ARMII KRAJOWEJ"},{"key":"data_wyk_pom","value":"18991230"},{"key":"gatunek1","value":"Prunus cerasifera"},{"key":"gatunek","value":"śliwa ałycza"},{"key":"wiek_w_dni","value":"0"},{"key":"jednostka","value":"Dzielnica Żoliborz"},{"key":"rank","value":"0.0706241"},{"key":"_full_count","value":"964"},{"key":"_id","value":"7010"},{"key":"dzielnica","value":"Żoliborz"},{"key":"stan_zdrowia","value":"dobry"},{"key":"miasto","value":"Warszawa"},{"key":"lokalizacja","value":"Ulica bez nazwy"},{"key":"numer_inw","value":"K12817"},{"key":"y","value":"5793467.46489511"},{"key":"x","value":"7497867.78587413"}]},{"properties":[{"key":"y_wgs84","value":"52.274755"},{"key":"x_wgs84","value":"20.96881"},{"key":"adres","value":"al. ARMII KRAJOWEJ"},{"key":"data_wyk_pom","value":"18991230"},{"key":"gatunek1","value":"Prunus cerasifera"},{"key":"gatunek","value":"śliwa ałycza"},{"key":"wiek_w_dni","value":"0"},{"key":"jednostka","value":"Dzielnica Żoliborz"},{"key":"rank","value":"0.0706241"},{"key":"_full_count","value":"964"},{"key":"_id","value":"7011"},{"key":"dzielnica","value":"Żoliborz"},{"key":"stan_zdrowia","value":"dobry"},{"key":"miasto","value":"Warszawa"},{"key":"lokalizacja","value":"Ulica bez nazwy"},{"key":"numer_inw","value":"K12818"},{"key":"y","value":"5793469.8827972"},{"key":"x","value":"7497871.21972028"}]},{"properties":[{"key":"y_wgs84","value":"52.274782"},{"key":"x_wgs84","value":"20.968872"},{"key":"adres","value":"al. ARMII KRAJOWEJ"},{"key":"data_wyk_pom","value":"18991230"},{"key":"gatunek1","value":"Prunus cerasifera"},{"key":"gatunek","value":"śliwa ałycza"},{"key":"wiek_w_dni","value":"0"},{"key":"jednostka","value":"Dzielnica Żoliborz"},{"key":"rank","value":"0.0706241"},{"key":"_full_count","value":"964"},{"key":"_id","value":"7012"},{"key":"dzielnica","value":"Żoliborz"},{"key":"stan_zdrowia","value":"dobry"},{"key":"miasto","value":"Warszawa"},{"key":"lokalizacja","value":"Ulica bez nazwy"},{"key":"numer_inw","value":"K12819"},{"key":"y","value":"5793472.80237762"},{"key":"x","value":"7497875.4772028"}]},{"properties":[{"key":"y_wgs84","value":"52.274889"},{"key":"x_wgs84","value":"20.969114"},{"key":"adres","value":"al. ARMII KRAJOWEJ"},{"key":"data_wyk_pom","value":"18991230"},{"key":"gatunek1","value":"Prunus cerasifera"},{"key":"gatunek","value":"śliwa ałycza"},{"key":"wiek_w_dni","value":"0"},{"key":"jednostka","value":"Dzielnica Żoliborz"},{"key":"rank","value":"0.0706241"},{"key":"_full_count","value":"964"},{"key":"_id","value":"7013"},{"key":"dzielnica","value":"Żoliborz"},{"key":"stan_zdrowia","value":"dobry"},{"key":"miasto","value":"Warszawa"},{"key":"lokalizacja","value":"Ulica bez nazwy"},{"key":"numer_inw","value":"K12820"},{"key":"y","value":"5793484.75636364"},{"key":"x","value":"7497892.00391608"}]},{"properties":[{"key":"y_wgs84","value":"52.274912"},{"key":"x_wgs84","value":"20.969182"},{"key":"adres","value":"al. ARMII KRAJOWEJ"},{"key":"data_wyk_pom","value":"18991230"},{"key":"gatunek1","value":"Prunus cerasifera"},{"key":"gatunek","value":"śliwa ałycza"},{"key":"wiek_w_dni","value":"0"},{"key":"jednostka","value":"Dzielnica Żoliborz"},{"key":"rank","value":"0.0706241"},{"key":"_full_count","value":"964"},{"key":"_id","value":"7014"},{"key":"dzielnica","value":"Żoliborz"},{"key":"stan_zdrowia","value":"dobry"},{"key":"miasto","value":"Warszawa"},{"key":"lokalizacja","value":"Ulica bez nazwy"},{"key":"numer_inw","value":"K12821"},{"key":"y","value":"5793487.31076923"},{"key":"x","value":"7497896.62727273"}]},{"properties":[{"key":"y_wgs84","value":"52.27561"},{"key":"x_wgs84","value":"20.970457"},{"key":"adres","value":"ul. OKSYWSKA"},{"key":"data_wyk_pom","value":"18991230"},{"key":"gatunek1","value":"Spiraea xvanhouttei"},{"key":"gatunek","value":"tawuła van Houtte\"a"},{"key":"wiek_w_dni","value":"0"},{"key":"jednostka","value":"Dzielnica Żoliborz"},{"key":"rank","value":"0.0706241"},{"key":"_full_count","value":"964"},{"key":"_id","value":"7015"},{"key":"dzielnica","value":"Żoliborz"},{"key":"stan_zdrowia","value":"dobry"},{"key":"miasto","value":"Warszawa"},{"key":"lokalizacja","value":"Ulica bez nazwy"},{"key":"numer_inw","value":"K12822"},{"key":"y","value":"5793564.97118881"},{"key":"x","value":"7497983.70601399"}]},{"properties":[{"key":"y_wgs84","value":"52.276507"},{"key":"x_wgs84","value":"20.972185"},{"key":"adres","value":"al. ARMII KRAJOWEJ"},{"key":"data_wyk_pom","value":"18991230"},{"key":"gatunek1","value":"Rosa  sp."},{"key":"gatunek","value":"róża  sp."},{"key":"wiek_w_dni","value":"0"},{"key":"jednostka","value":"Dzielnica Żoliborz"},{"key":"rank","value":"0.0706241"},{"key":"_full_count","value":"964"},{"key":"_id","value":"7016"},{"key":"dzielnica","value":"Żoliborz"},{"key":"stan_zdrowia","value":"dobry"},{"key":"miasto","value":"Warszawa"},{"key":"lokalizacja","value":"Ulica bez nazwy"},{"key":"numer_inw","value":"K12823"},{"key":"y","value":"5793664.71524476"},{"key":"x","value":"7498101.63594406"}]},{"properties":[{"key":"y_wgs84","value":"52.275234"},{"key":"x_wgs84","value":"20.970902"},{"key":"adres","value":"al. ARMII KRAJOWEJ"},{"key":"data_wyk_pom","value":"18991230"},{"key":"gatunek1","value":"Hippophae rhamnoides"},{"key":"gatunek","value":"rokitnik pospolity"},{"key":"wiek_w_dni","value":"0"},{"key":"jednostka","value":"Dzielnica Żoliborz"},{"key":"rank","value":"0.0706241"},{"key":"_full_count","value":"964"},{"key":"_id","value":"6751"},{"key":"dzielnica","value":"Żoliborz"},{"key":"stan_zdrowia","value":"dobry"},{"key":"miasto","value":"Warszawa"},{"key":"lokalizacja","value":"Ulica bez nazwy"},{"key":"numer_inw","value":"K12775"},{"key":"y","value":"5793523.1434965"},{"key":"x","value":"7498014.03174825"}]},{"properties":[{"key":"y_wgs84","value":"52.267873"},{"key":"x_wgs84","value":"20.98688"},{"key":"adres","value":"ul. MICKIEWICZA A"},{"key":"data_wyk_pom","value":"18991230"},{"key":"gatunek1","value":"Sambucus nigra"},{"key":"gatunek","value":"bez czarny"},{"key":"wiek_w_dni","value":"0"},{"key":"jednostka","value":"Dzielnica Żoliborz"},{"key":"rank","value":"0.0706241"},{"key":"_full_count","value":"964"},{"key":"_id","value":"6316"},{"key":"dzielnica","value":"Żoliborz"},{"key":"stan_zdrowia","value":"dobry"},{"key":"miasto","value":"Warszawa"},{"key":"lokalizacja","value":"Ulica bez nazwy"},{"key":"numer_inw","value":"K12653"},{"key":"y","value":"5792703.78769231"},{"key":"x","value":"7499104.43412587"}]},{"properties":[{"key":"y_wgs84","value":"52.267726"},{"key":"x_wgs84","value":"20.986988"},{"key":"adres","value":"ul. MICKIEWICZA A"},{"key":"data_wyk_pom","value":"18991230"},{"key":"gatunek1","value":"Lonicera  sp."},{"key":"gatunek","value":"wiciokrzew  sp."},{"key":"wiek_w_dni","value":"0"},{"key":"jednostka","value":"Dzielnica Żoliborz"},{"key":"rank","value":"0.0706241"},{"key":"_full_count","value":"964"},{"key":"_id","value":"6317"},{"key":"dzielnica","value":"Żoliborz"},{"key":"stan_zdrowia","value":"dobry"},{"key":"miasto","value":"Warszawa"},{"key":"lokalizacja","value":"Ulica bez nazwy"},{"key":"numer_inw","value":"K12654"},{"key":"y","value":"5792687.39496503"},{"key":"x","value":"7499111.8006993"}]},{"properties":[{"key":"y_wgs84","value":"52.267707"},{"key":"x_wgs84","value":"20.987001"},{"key":"adres","value":"ul. MICKIEWICZA A"},{"key":"data_wyk_pom","value":"18991230"},{"key":"gatunek1","value":"Lonicera  sp."},{"key":"gatunek","value":"wiciokrzew  sp."},{"key":"wiek_w_dni","value":"0"},{"key":"jednostka","value":"Dzielnica Żoliborz"},{"key":"rank","value":"0.0706241"},{"key":"_full_count","value":"964"},{"key":"_id","value":"6318"},{"key":"dzielnica","value":"Żoliborz"},{"key":"stan_zdrowia","value":"dobry"},{"key":"miasto","value":"Warszawa"},{"key":"lokalizacja","value":"Ulica bez nazwy"},{"key":"numer_inw","value":"K12655"},{"key":"y","value":"5792685.29496504"},{"key":"x","value":"7499112.66979021"}]},{"properties":[{"key":"y_wgs84","value":"52.264948"},{"key":"x_wgs84","value":"20.983083"},{"key":"adres","value":"ul. WIENIAWSKIEGO H"},{"key":"data_wyk_pom","value":"18991230"},{"key":"gatunek1","value":"Forsythia  sp."},{"key":"gatunek","value":"forsycja  sp."},{"key":"wiek_w_dni","value":"0"},{"key":"jednostka","value":"Dzielnica Żoliborz"},{"key":"rank","value":"0.0706241"},{"key":"_full_count","value":"964"},{"key":"_id","value":"6508"},{"key":"dzielnica","value":"Żoliborz"},{"key":"stan_zdrowia","value":"średni"},{"key":"miasto","value":"Warszawa"},{"key":"lokalizacja","value":"Ulica bez nazwy"},{"key":"numer_inw","value":"K13236"},{"key":"y","value":"5792378.38041958"},{"key":"x","value":"7498845.14433566"}]},{"properties":[{"key":"y_wgs84","value":"52.267573"},{"key":"x_wgs84","value":"20.987131"},{"key":"adres","value":"ul. MICKIEWICZA A"},{"key":"data_wyk_pom","value":"18991230"},{"key":"gatunek1","value":"Philadelphus coronarius"},{"key":"gatunek","value":"jaśminowiec wonny"},{"key":"wiek_w_dni","value":"0"},{"key":"jednostka","value":"Dzielnica Żoliborz"},{"key":"rank","value":"0.0706241"},{"key":"_full_count","value":"964"},{"key":"_id","value":"6320"},{"key":"dzielnica","value":"Żoliborz"},{"key":"stan_zdrowia","value":"dobry"},{"key":"miasto","value":"Warszawa"},{"key":"lokalizacja","value":"Ulica bez nazwy"},{"key":"numer_inw","value":"K12657"},{"key":"y","value":"5792670.40839161"},{"key":"x","value":"7499121.50167832"}]},{"properties":[{"key":"y_wgs84","value":"52.267551"},{"key":"x_wgs84","value":"20.987149"},{"key":"adres","value":"ul. MICKIEWICZA A"},{"key":"data_wyk_pom","value":"18991230"},{"key":"gatunek1","value":"Philadelphus coronarius"},{"key":"gatunek","value":"jaśminowiec wonny"},{"key":"wiek_w_dni","value":"0"},{"key":"jednostka","value":"Dzielnica Żoliborz"},{"key":"rank","value":"0.0706241"},{"key":"_full_count","value":"964"},{"key":"_id","value":"6321"},{"key":"dzielnica","value":"Żoliborz"},{"key":"stan_zdrowia","value":"dobry"},{"key":"miasto","value":"Warszawa"},{"key":"lokalizacja","value":"Ulica bez nazwy"},{"key":"numer_inw","value":"K12658"},{"key":"y","value":"5792667.89734266"},{"key":"x","value":"7499122.78293706"}]},{"properties":[{"key":"y_wgs84","value":"52.267576"},{"key":"x_wgs84","value":"20.987168"},{"key":"adres","value":"ul. MICKIEWICZA A"},{"key":"data_wyk_pom","value":"18991230"},{"key":"gatunek1","value":"Symphoricarpos albus"},{"key":"gatunek","value":"śnieguliczka biała"},{"key":"wiek_w_dni","value":"0"},{"key":"jednostka","value":"Dzielnica Żoliborz"},{"key":"rank","value":"0.0706241"},{"key":"_full_count","value":"964"},{"key":"_id","value":"6322"},{"key":"dzielnica","value":"Żoliborz"},{"key":"stan_zdrowia","value":"dobry"},{"key":"miasto","value":"Warszawa"},{"key":"lokalizacja","value":"Ulica bez nazwy"},{"key":"numer_inw","value":"K12659"},{"key":"y","value":"5792670.68195804"},{"key":"x","value":"7499124.06503497"}]},{"properties":[{"key":"y_wgs84","value":"52.267556"},{"key":"x_wgs84","value":"20.987178"},{"key":"adres","value":"ul. MICKIEWICZA A"},{"key":"data_wyk_pom","value":"18991230"},{"key":"gatunek1","value":"Symphoricarpos albus"},{"key":"gatunek","value":"śnieguliczka biała"},{"key":"wiek_w_dni","value":"0"},{"key":"jednostka","value":"Dzielnica Żoliborz"},{"key":"rank","value":"0.0706241"},{"key":"_full_count","value":"964"},{"key":"_id","value":"6323"},{"key":"dzielnica","value":"Żoliborz"},{"key":"stan_zdrowia","value":"dobry"},{"key":"miasto","value":"Warszawa"},{"key":"lokalizacja","value":"Ulica bez nazwy"},{"key":"numer_inw","value":"K12660"},{"key":"y","value":"5792668.53608392"},{"key":"x","value":"7499124.75146853"}]},{"properties":[{"key":"y_wgs84","value":"52.267458"},{"key":"x_wgs84","value":"20.987255"},{"key":"adres","value":"ul. MICKIEWICZA A"},{"key":"data_wyk_pom","value":"18991230"},{"key":"gatunek1","value":"Lonicera  sp."},{"key":"gatunek","value":"wiciokrzew  sp."},{"key":"wiek_w_dni","value":"0"},{"key":"jednostka","value":"Dzielnica Żoliborz"},{"key":"rank","value":"0.0706241"},{"key":"_full_count","value":"964"},{"key":"_id","value":"6324"},{"key":"dzielnica","value":"Żoliborz"},{"key":"stan_zdrowia","value":"dobry"},{"key":"miasto","value":"Warszawa"},{"key":"lokalizacja","value":"Ulica bez nazwy"},{"key":"numer_inw","value":"K12661"},{"key":"y","value":"5792657.53132867"},{"key":"x","value":"7499129.96727273"}]},{"properties":[{"key":"y_wgs84","value":"52.267283"},{"key":"x_wgs84","value":"20.987418"},{"key":"adres","value":"ul. MICKIEWICZA A"},{"key":"data_wyk_pom","value":"18991230"},{"key":"gatunek1","value":"Syringa vulgaris"},{"key":"gatunek","value":"lilak pospolity"},{"key":"wiek_w_dni","value":"0"},{"key":"jednostka","value":"Dzielnica Żoliborz"},{"key":"rank","value":"0.0706241"},{"key":"_full_count","value":"964"},{"key":"_id","value":"6325"},{"key":"dzielnica","value":"Żoliborz"},{"key":"stan_zdrowia","value":"dobry"},{"key":"miasto","value":"Warszawa"},{"key":"lokalizacja","value":"Ulica bez nazwy"},{"key":"numer_inw","value":"K12662"},{"key":"y","value":"5792638.12461538"},{"key":"x","value":"7499141.13300699"}]},{"properties":[{"key":"y_wgs84","value":"52.267257"},{"key":"x_wgs84","value":"20.987418"},{"key":"adres","value":"ul. MICKIEWICZA A"},{"key":"data_wyk_pom","value":"18991230"},{"key":"gatunek1","value":"Lonicera  sp."},{"key":"gatunek","value":"wiciokrzew  sp."},{"key":"wiek_w_dni","value":"0"},{"key":"jednostka","value":"Dzielnica Żoliborz"},{"key":"rank","value":"0.0706241"},{"key":"_full_count","value":"964"},{"key":"_id","value":"6326"},{"key":"dzielnica","value":"Żoliborz"},{"key":"stan_zdrowia","value":"dobry"},{"key":"miasto","value":"Warszawa"},{"key":"lokalizacja","value":"Ulica bez nazwy"},{"key":"numer_inw","value":"K12663"},{"key":"y","value":"5792635.24797203"},{"key":"x","value":"7499141.13258741"}]},{"properties":[{"key":"y_wgs84","value":"52.267253"},{"key":"x_wgs84","value":"20.987406"},{"key":"adres","value":"ul. MICKIEWICZA A"},{"key":"data_wyk_pom","value":"18991230"},{"key":"gatunek1","value":"Philadelphus coronarius"},{"key":"gatunek","value":"jaśminowiec wonny"},{"key":"wiek_w_dni","value":"0"},{"key":"jednostka","value":"Dzielnica Żoliborz"},{"key":"rank","value":"0.0706241"},{"key":"_full_count","value":"964"},{"key":"_id","value":"6327"},{"key":"dzielnica","value":"Żoliborz"},{"key":"stan_zdrowia","value":"dobry"},{"key":"miasto","value":"Warszawa"},{"key":"lokalizacja","value":"Ulica bez nazwy"},{"key":"numer_inw","value":"K12664"},{"key":"y","value":"5792634.74587413"},{"key":"x","value":"7499140.26293706"}]},{"properties":[{"key":"y_wgs84","value":"52.267217"},{"key":"x_wgs84","value":"20.987509"},{"key":"adres","value":"ul. MICKIEWICZA A"},{"key":"data_wyk_pom","value":"18991230"},{"key":"gatunek1","value":"Syringa vulgaris"},{"key":"gatunek","value":"lilak pospolity"},{"key":"wiek_w_dni","value":"0"},{"key":"jednostka","value":"Dzielnica Żoliborz"},{"key":"rank","value":"0.0706241"},{"key":"_full_count","value":"964"},{"key":"_id","value":"6328"},{"key":"dzielnica","value":"Żoliborz"},{"key":"stan_zdrowia","value":"dobry"},{"key":"miasto","value":"Warszawa"},{"key":"lokalizacja","value":"Ulica bez nazwy"},{"key":"numer_inw","value":"K12665"},{"key":"y","value":"5792630.72657343"},{"key":"x","value":"7499147.31118881"}]},{"properties":[{"key":"y_wgs84","value":"52.267171"},{"key":"x_wgs84","value":"20.987474"},{"key":"adres","value":"ul. MICKIEWICZA A"},{"key":"data_wyk_pom","value":"18991230"},{"key":"gatunek1","value":"Corylus avellana"},{"key":"gatunek","value":"leszczyna pospolita"},{"key":"wiek_w_dni","value":"0"},{"key":"jednostka","value":"Dzielnica Żoliborz"},{"key":"rank","value":"0.0706241"},{"key":"_full_count","value":"964"},{"key":"_id","value":"6329"},{"key":"dzielnica","value":"Żoliborz"},{"key":"stan_zdrowia","value":"dobry"},{"key":"miasto","value":"Warszawa"},{"key":"lokalizacja","value":"Ulica bez nazwy"},{"key":"numer_inw","value":"K12666"},{"key":"y","value":"5792625.61342657"},{"key":"x","value":"7499144.92979021"}]},{"properties":[{"key":"y_wgs84","value":"52.267183"},{"key":"x_wgs84","value":"20.987509"},{"key":"adres","value":"ul. MICKIEWICZA A"},{"key":"data_wyk_pom","value":"18991230"},{"key":"gatunek1","value":"Sambucus nigra"},{"key":"gatunek","value":"bez czarny"},{"key":"wiek_w_dni","value":"0"},{"key":"jednostka","value":"Dzielnica Żoliborz"},{"key":"rank","value":"0.0706241"},{"key":"_full_count","value":"964"},{"key":"_id","value":"6330"},{"key":"dzielnica","value":"Żoliborz"},{"key":"stan_zdrowia","value":"zły"},{"key":"miasto","value":"Warszawa"},{"key":"lokalizacja","value":"Ulica bez nazwy"},{"key":"numer_inw","value":"K12667"},{"key":"y","value":"5792626.98251748"},{"key":"x","value":"7499147.31048951"}]},{"properties":[{"key":"y_wgs84","value":"52.267149"},{"key":"x_wgs84","value":"20.987503"},{"key":"adres","value":"ul. MICKIEWICZA A"},{"key":"data_wyk_pom","value":"18991230"},{"key":"gatunek1","value":"Philadelphus coronarius"},{"key":"gatunek","value":"jaśminowiec wonny"},{"key":"wiek_w_dni","value":"0"},{"key":"jednostka","value":"Dzielnica Żoliborz"},{"key":"rank","value":"0.0706241"},{"key":"_full_count","value":"964"},{"key":"_id","value":"6331"},{"key":"dzielnica","value":"Żoliborz"},{"key":"stan_zdrowia","value":"dobry"},{"key":"miasto","value":"Warszawa"},{"key":"lokalizacja","value":"Ulica bez nazwy"},{"key":"numer_inw","value":"K12668"},{"key":"y","value":"5792623.2386014"},{"key":"x","value":"7499146.89776224"}]},{"properties":[{"key":"y_wgs84","value":"52.267096"},{"key":"x_wgs84","value":"20.98754"},{"key":"adres","value":"ul. MICKIEWICZA A"},{"key":"data_wyk_pom","value":"18991230"},{"key":"gatunek1","value":"Forsythia  sp."},{"key":"gatunek","value":"forsycja  sp."},{"key":"wiek_w_dni","value":"0"},{"key":"jednostka","value":"Dzielnica Żoliborz"},{"key":"rank","value":"0.0706241"},{"key":"_full_count","value":"964"},{"key":"_id","value":"6332"},{"key":"dzielnica","value":"Żoliborz"},{"key":"stan_zdrowia","value":"dobry"},{"key":"miasto","value":"Warszawa"},{"key":"lokalizacja","value":"Ulica bez nazwy"},{"key":"numer_inw","value":"K12669"},{"key":"y","value":"5792617.2572028"},{"key":"x","value":"7499149.41468531"}]},{"properties":[{"key":"y_wgs84","value":"52.267076"},{"key":"x_wgs84","value":"20.987557"},{"key":"adres","value":"ul. MICKIEWICZA A"},{"key":"data_wyk_pom","value":"18991230"},{"key":"gatunek1","value":"Philadelphus coronarius"},{"key":"gatunek","value":"jaśminowiec wonny"},{"key":"wiek_w_dni","value":"0"},{"key":"jednostka","value":"Dzielnica Żoliborz"},{"key":"rank","value":"0.0706241"},{"key":"_full_count","value":"964"},{"key":"_id","value":"6333"},{"key":"dzielnica","value":"Żoliborz"},{"key":"stan_zdrowia","value":"dobry"},{"key":"miasto","value":"Warszawa"},{"key":"lokalizacja","value":"Ulica bez nazwy"},{"key":"numer_inw","value":"K12670"},{"key":"y","value":"5792615.11118881"},{"key":"x","value":"7499150.60447552"}]},{"properties":[{"key":"y_wgs84","value":"52.267082"},{"key":"x_wgs84","value":"20.987588"},{"key":"adres","value":"ul. MICKIEWICZA A"},{"key":"data_wyk_pom","value":"18991230"},{"key":"gatunek1","value":"Symphoricarpos albus"},{"key":"gatunek","value":"śnieguliczka biała"},{"key":"wiek_w_dni","value":"0"},{"key":"jednostka","value":"Dzielnica Żoliborz"},{"key":"rank","value":"0.0706241"},{"key":"_full_count","value":"964"},{"key":"_id","value":"6334"},{"key":"dzielnica","value":"Żoliborz"},{"key":"stan_zdrowia","value":"dobry"},{"key":"miasto","value":"Warszawa"},{"key":"lokalizacja","value":"Ulica bez nazwy"},{"key":"numer_inw","value":"K12671"},{"key":"y","value":"5792615.75006993"},{"key":"x","value":"7499152.70979021"}]},{"properties":[{"key":"y_wgs84","value":"52.267085"},{"key":"x_wgs84","value":"20.987615"},{"key":"adres","value":"ul. MICKIEWICZA A"},{"key":"data_wyk_pom","value":"18991230"},{"key":"gatunek1","value":"Symphoricarpos albus"},{"key":"gatunek","value":"śnieguliczka biała"},{"key":"wiek_w_dni","value":"0"},{"key":"jednostka","value":"Dzielnica Żoliborz"},{"key":"rank","value":"0.0706241"},{"key":"_full_count","value":"964"},{"key":"_id","value":"6335"},{"key":"dzielnica","value":"Żoliborz"},{"key":"stan_zdrowia","value":"dobry"},{"key":"miasto","value":"Warszawa"},{"key":"lokalizacja","value":"Ulica bez nazwy"},{"key":"numer_inw","value":"K12672"},{"key":"y","value":"5792616.11496503"},{"key":"x","value":"7499154.58699301"}]},{"properties":[{"key":"y_wgs84","value":"52.267062"},{"key":"x_wgs84","value":"20.987639"},{"key":"adres","value":"ul. MICKIEWICZA A"},{"key":"data_wyk_pom","value":"18991230"},{"key":"gatunek1","value":"Symphoricarpos albus"},{"key":"gatunek","value":"śnieguliczka biała"},{"key":"wiek_w_dni","value":"0"},{"key":"jednostka","value":"Dzielnica Żoliborz"},{"key":"rank","value":"0.0706241"},{"key":"_full_count","value":"964"},{"key":"_id","value":"6336"},{"key":"dzielnica","value":"Żoliborz"},{"key":"stan_zdrowia","value":"dobry"},{"key":"miasto","value":"Warszawa"},{"key":"lokalizacja","value":"Ulica bez nazwy"},{"key":"numer_inw","value":"K12673"},{"key":"y","value":"5792613.46601399"},{"key":"x","value":"7499156.18825175"}]},{"properties":[{"key":"y_wgs84","value":"52.267041"},{"key":"x_wgs84","value":"20.987661"},{"key":"adres","value":"ul. MICKIEWICZA A"},{"key":"data_wyk_pom","value":"18991230"},{"key":"gatunek1","value":"Spiraea xvanhouttei"},{"key":"gatunek","value":"tawuła van Houtte\"a"},{"key":"wiek_w_dni","value":"0"},{"key":"jednostka","value":"Dzielnica Żoliborz"},{"key":"rank","value":"0.0706241"},{"key":"_full_count","value":"964"},{"key":"_id","value":"6337"},{"key":"dzielnica","value":"Żoliborz"},{"key":"stan_zdrowia","value":"dobry"},{"key":"miasto","value":"Warszawa"},{"key":"lokalizacja","value":"Ulica bez nazwy"},{"key":"numer_inw","value":"K12674"},{"key":"y","value":"5792611.1372028"},{"key":"x","value":"7499157.69874126"}]},{"properties":[{"key":"y_wgs84","value":"52.266924"},{"key":"x_wgs84","value":"20.98778"},{"key":"adres","value":"ul. MICKIEWICZA A"},{"key":"data_wyk_pom","value":"18991230"},{"key":"gatunek1","value":"Sambucus nigra"},{"key":"gatunek","value":"bez czarny"},{"key":"wiek_w_dni","value":"0"},{"key":"jednostka","value":"Dzielnica Żoliborz"},{"key":"rank","value":"0.0706241"},{"key":"_full_count","value":"964"},{"key":"_id","value":"6338"},{"key":"dzielnica","value":"Żoliborz"},{"key":"stan_zdrowia","value":"dobry"},{"key":"miasto","value":"Warszawa"},{"key":"lokalizacja","value":"Ulica bez nazwy"},{"key":"numer_inw","value":"K12675"},{"key":"y","value":"5792598.16881119"},{"key":"x","value":"7499165.84447552"}]},{"properties":[{"key":"y_wgs84","value":"52.266902"},{"key":"x_wgs84","value":"20.987764"},{"key":"adres","value":"ul. MICKIEWICZA A"},{"key":"data_wyk_pom","value":"18991230"},{"key":"gatunek1","value":"Sambucus nigra"},{"key":"gatunek","value":"bez czarny"},{"key":"wiek_w_dni","value":"0"},{"key":"jednostka","value":"Dzielnica Żoliborz"},{"key":"rank","value":"0.0706241"},{"key":"_full_count","value":"964"},{"key":"_id","value":"6339"},{"key":"dzielnica","value":"Żoliborz"},{"key":"stan_zdrowia","value":"dobry"},{"key":"miasto","value":"Warszawa"},{"key":"lokalizacja","value":"Ulica bez nazwy"},{"key":"numer_inw","value":"K12676"},{"key":"y","value":"5792595.70335664"},{"key":"x","value":"7499164.74517483"}]},{"properties":[{"key":"y_wgs84","value":"52.266882"},{"key":"x_wgs84","value":"20.987745"},{"key":"adres","value":"ul. MICKIEWICZA A"},{"key":"data_wyk_pom","value":"18991230"},{"key":"gatunek1","value":"Sambucus nigra"},{"key":"gatunek","value":"bez czarny"},{"key":"wiek_w_dni","value":"0"},{"key":"jednostka","value":"Dzielnica Żoliborz"},{"key":"rank","value":"0.0706241"},{"key":"_full_count","value":"964"},{"key":"_id","value":"6340"},{"key":"dzielnica","value":"Żoliborz"},{"key":"stan_zdrowia","value":"dobry"},{"key":"miasto","value":"Warszawa"},{"key":"lokalizacja","value":"Ulica bez nazwy"},{"key":"numer_inw","value":"K12677"},{"key":"y","value":"5792593.46671329"},{"key":"x","value":"7499163.46307692"}]},{"properties":[{"key":"y_wgs84","value":"52.266629"},{"key":"x_wgs84","value":"20.988045"},{"key":"adres","value":"ul. MICKIEWICZA A"},{"key":"data_wyk_pom","value":"18991230"},{"key":"gatunek1","value":"Sambucus nigra"},{"key":"gatunek","value":"bez czarny"},{"key":"wiek_w_dni","value":"0"},{"key":"jednostka","value":"Dzielnica Żoliborz"},{"key":"rank","value":"0.0706241"},{"key":"_full_count","value":"964"},{"key":"_id","value":"6341"},{"key":"dzielnica","value":"Żoliborz"},{"key":"stan_zdrowia","value":"dobry"},{"key":"miasto","value":"Warszawa"},{"key":"lokalizacja","value":"Ulica bez nazwy"},{"key":"numer_inw","value":"K12678"},{"key":"y","value":"5792565.3827972"},{"key":"x","value":"7499183.87384615"}]},{"properties":[{"key":"y_wgs84","value":"52.266566"},{"key":"x_wgs84","value":"20.988026"},{"key":"adres","value":"ul. MICKIEWICZA A"},{"key":"data_wyk_pom","value":"18991230"},{"key":"gatunek1","value":"Sambucus nigra"},{"key":"gatunek","value":"bez czarny"},{"key":"wiek_w_dni","value":"0"},{"key":"jednostka","value":"Dzielnica Żoliborz"},{"key":"rank","value":"0.0706241"},{"key":"_full_count","value":"964"},{"key":"_id","value":"6342"},{"key":"dzielnica","value":"Żoliborz"},{"key":"stan_zdrowia","value":"dobry"},{"key":"miasto","value":"Warszawa"},{"key":"lokalizacja","value":"Ulica bez nazwy"},{"key":"numer_inw","value":"K12679"},{"key":"y","value":"5792558.35118881"},{"key":"x","value":"7499182.59104895"}]},{"properties":[{"key":"y_wgs84","value":"52.266518"},{"key":"x_wgs84","value":"20.988081"},{"key":"adres","value":"ul. MICKIEWICZA A"},{"key":"data_wyk_pom","value":"18991230"},{"key":"gatunek1","value":"Forsythia  sp."},{"key":"gatunek","value":"forsycja  sp."},{"key":"wiek_w_dni","value":"0"},{"key":"jednostka","value":"Dzielnica Żoliborz"},{"key":"rank","value":"0.0706241"},{"key":"_full_count","value":"964"},{"key":"_id","value":"6343"},{"key":"dzielnica","value":"Żoliborz"},{"key":"stan_zdrowia","value":"dobry"},{"key":"miasto","value":"Warszawa"},{"key":"lokalizacja","value":"Ulica bez nazwy"},{"key":"numer_inw","value":"K12680"},{"key":"y","value":"5792552.9627972"},{"key":"x","value":"7499186.34377622"}]},{"properties":[{"key":"y_wgs84","value":"52.266502"},{"key":"x_wgs84","value":"20.988077"},{"key":"adres","value":"ul. MICKIEWICZA A"},{"key":"data_wyk_pom","value":"18991230"},{"key":"gatunek1","value":"Philadelphus  sp."},{"key":"gatunek","value":"jaśminowiec  sp."},{"key":"wiek_w_dni","value":"0"},{"key":"jednostka","value":"Dzielnica Żoliborz"},{"key":"rank","value":"0.0706241"},{"key":"_full_count","value":"964"},{"key":"_id","value":"6344"},{"key":"dzielnica","value":"Żoliborz"},{"key":"stan_zdrowia","value":"dobry"},{"key":"miasto","value":"Warszawa"},{"key":"lokalizacja","value":"Ulica bez nazwy"},{"key":"numer_inw","value":"K12681"},{"key":"y","value":"5792551.18223776"},{"key":"x","value":"7499186.11412587"}]},{"properties":[{"key":"y_wgs84","value":"52.266481"},{"key":"x_wgs84","value":"20.988092"},{"key":"adres","value":"ul. MICKIEWICZA A"},{"key":"data_wyk_pom","value":"18991230"},{"key":"gatunek1","value":"Spiraea japonica"},{"key":"gatunek","value":"tawuła japońska"},{"key":"wiek_w_dni","value":"0"},{"key":"jednostka","value":"Dzielnica Żoliborz"},{"key":"rank","value":"0.0706241"},{"key":"_full_count","value":"964"},{"key":"_id","value":"6345"},{"key":"dzielnica","value":"Żoliborz"},{"key":"stan_zdrowia","value":"dobry"},{"key":"miasto","value":"Warszawa"},{"key":"lokalizacja","value":"Ulica bez nazwy"},{"key":"numer_inw","value":"K12682"},{"key":"y","value":"5792548.8993007"},{"key":"x","value":"7499187.12125874"}]},{"properties":[{"key":"y_wgs84","value":"52.26649"},{"key":"x_wgs84","value":"20.9881"},{"key":"adres","value":"ul. MICKIEWICZA A"},{"key":"data_wyk_pom","value":"18991230"},{"key":"gatunek1","value":"Chaenomeles  sp."},{"key":"gatunek","value":"pigwowiec  sp."},{"key":"wiek_w_dni","value":"0"},{"key":"jednostka","value":"Dzielnica Żoliborz"},{"key":"rank","value":"0.0706241"},{"key":"_full_count","value":"964"},{"key":"_id","value":"6346"},{"key":"dzielnica","value":"Żoliborz"},{"key":"stan_zdrowia","value":"dobry"},{"key":"miasto","value":"Warszawa"},{"key":"lokalizacja","value":"Ulica bez nazwy"},{"key":"numer_inw","value":"K12683"},{"key":"y","value":"5792549.81188811"},{"key":"x","value":"7499187.67034965"}]},{"properties":[{"key":"y_wgs84","value":"52.266401"},{"key":"x_wgs84","value":"20.988194"},{"key":"adres","value":"ul. MICKIEWICZA A"},{"key":"data_wyk_pom","value":"18991230"},{"key":"gatunek1","value":"Sambucus nigra"},{"key":"gatunek","value":"bez czarny"},{"key":"wiek_w_dni","value":"0"},{"key":"jednostka","value":"Dzielnica Żoliborz"},{"key":"rank","value":"0.0706241"},{"key":"_full_count","value":"964"},{"key":"_id","value":"6347"},{"key":"dzielnica","value":"Żoliborz"},{"key":"stan_zdrowia","value":"dobry"},{"key":"miasto","value":"Warszawa"},{"key":"lokalizacja","value":"Ulica bez nazwy"},{"key":"numer_inw","value":"K12684"},{"key":"y","value":"5792539.99454545"},{"key":"x","value":"7499194.07748252"}]},{"properties":[{"key":"y_wgs84","value":"52.261574"},{"key":"x_wgs84","value":"20.991266"},{"key":"adres","value":"ul. ZAJĄCZKA J GEN"},{"key":"data_wyk_pom","value":"18991230"},{"key":"gatunek1","value":"Berberis  sp."},{"key":"gatunek","value":"berberys  sp."},{"key":"wiek_w_dni","value":"0"},{"key":"jednostka","value":"Dzielnica Żoliborz"},{"key":"rank","value":"0.0706241"},{"key":"_full_count","value":"964"},{"key":"_id","value":"6348"},{"key":"dzielnica","value":"Żoliborz"},{"key":"stan_zdrowia","value":"dobry"},{"key":"miasto","value":"Warszawa"},{"key":"lokalizacja","value":"Ulica bez nazwy"},{"key":"numer_inw","value":"K13179"},{"key":"y","value":"5792002.88797203"},{"key":"x","value":"7499403.70699301"}]},{"properties":[{"key":"y_wgs84","value":"52.261579"},{"key":"x_wgs84","value":"20.991226"},{"key":"adres","value":"ul. ZAJĄCZKA J GEN"},{"key":"data_wyk_pom","value":"18991230"},{"key":"gatunek1","value":"Sambucus nigra"},{"key":"gatunek","value":"bez czarny"},{"key":"wiek_w_dni","value":"0"},{"key":"jednostka","value":"Dzielnica Żoliborz"},{"key":"rank","value":"0.0706241"},{"key":"_full_count","value":"964"},{"key":"_id","value":"6349"},{"key":"dzielnica","value":"Żoliborz"},{"key":"stan_zdrowia","value":"dobry"},{"key":"miasto","value":"Warszawa"},{"key":"lokalizacja","value":"Ulica bez nazwy"},{"key":"numer_inw","value":"K13180"},{"key":"y","value":"5792003.43636364"},{"key":"x","value":"7499400.96013986"}]},{"properties":[{"key":"y_wgs84","value":"52.261573"},{"key":"x_wgs84","value":"20.991049"},{"key":"adres","value":"ul. ZAJĄCZKA J GEN"},{"key":"data_wyk_pom","value":"18991230"},{"key":"gatunek1","value":"Pyracantha coccinea"},{"key":"gatunek","value":"ognik szkarłatny"},{"key":"wiek_w_dni","value":"0"},{"key":"jednostka","value":"Dzielnica Żoliborz"},{"key":"rank","value":"0.0706241"},{"key":"_full_count","value":"964"},{"key":"_id","value":"6350"},{"key":"dzielnica","value":"Żoliborz"},{"key":"stan_zdrowia","value":"dobry"},{"key":"miasto","value":"Warszawa"},{"key":"lokalizacja","value":"Ulica bez nazwy"},{"key":"numer_inw","value":"K13181"},{"key":"y","value":"5792002.70685315"},{"key":"x","value":"7499388.87440559"}]},{"properties":[{"key":"y_wgs84","value":"52.264839"},{"key":"x_wgs84","value":"20.983072"},{"key":"adres","value":"ul. WIENIAWSKIEGO H"},{"key":"data_wyk_pom","value":"18991230"},{"key":"gatunek1","value":"Juniperus  sp."},{"key":"gatunek","value":"jałowiec  sp."},{"key":"wiek_w_dni","value":"0"},{"key":"jednostka","value":"Dzielnica Żoliborz"},{"key":"rank","value":"0.0706241"},{"key":"_full_count","value":"964"},{"key":"_id","value":"6504"},{"key":"dzielnica","value":"Żoliborz"},{"key":"stan_zdrowia","value":"średni"},{"key":"miasto","value":"Warszawa"},{"key":"lokalizacja","value":"Ulica bez nazwy"},{"key":"numer_inw","value":"K13232"},{"key":"y","value":"5792366.18867133"},{"key":"x","value":"7498844.36335664"}]},{"properties":[{"key":"y_wgs84","value":"52.262572"},{"key":"x_wgs84","value":"20.989403"},{"key":"adres","value":"ul. LISA-KULI L"},{"key":"data_wyk_pom","value":"18991230"},{"key":"gatunek1","value":"Rosa  sp."},{"key":"gatunek","value":"róża  sp."},{"key":"wiek_w_dni","value":"0"},{"key":"jednostka","value":"Dzielnica Żoliborz"},{"key":"rank","value":"0.0706241"},{"key":"_full_count","value":"964"},{"key":"_id","value":"6352"},{"key":"dzielnica","value":"Żoliborz"},{"key":"stan_zdrowia","value":"dobry"},{"key":"miasto","value":"Warszawa"},{"key":"lokalizacja","value":"Ulica bez nazwy"},{"key":"numer_inw","value":"K13183"},{"key":"y","value":"5792113.91384615"},{"key":"x","value":"7499276.54727273"}]},{"properties":[{"key":"y_wgs84","value":"52.262569"},{"key":"x_wgs84","value":"20.989536"},{"key":"adres","value":"ul. LISA-KULI L"},{"key":"data_wyk_pom","value":"18991230"},{"key":"gatunek1","value":"Rosa  sp."},{"key":"gatunek","value":"róża  sp."},{"key":"wiek_w_dni","value":"0"},{"key":"jednostka","value":"Dzielnica Żoliborz"},{"key":"rank","value":"0.0706241"},{"key":"_full_count","value":"964"},{"key":"_id","value":"6353"},{"key":"dzielnica","value":"Żoliborz"},{"key":"stan_zdrowia","value":"dobry"},{"key":"miasto","value":"Warszawa"},{"key":"lokalizacja","value":"Ulica bez nazwy"},{"key":"numer_inw","value":"K13184"},{"key":"y","value":"5792113.63846154"},{"key":"x","value":"7499285.61146853"}]},{"properties":[{"key":"y_wgs84","value":"52.262568"},{"key":"x_wgs84","value":"20.989563"},{"key":"adres","value":"ul. LISA-KULI L"},{"key":"data_wyk_pom","value":"18991230"},{"key":"gatunek1","value":"Rosa  sp."},{"key":"gatunek","value":"róża  sp."},{"key":"wiek_w_dni","value":"0"},{"key":"jednostka","value":"Dzielnica Żoliborz"},{"key":"rank","value":"0.0706241"},{"key":"_full_count","value":"964"},{"key":"_id","value":"6354"},{"key":"dzielnica","value":"Żoliborz"},{"key":"stan_zdrowia","value":"dobry"},{"key":"miasto","value":"Warszawa"},{"key":"lokalizacja","value":"Ulica bez nazwy"},{"key":"numer_inw","value":"K13185"},{"key":"y","value":"5792113.50125874"},{"key":"x","value":"7499287.4420979"}]},{"properties":[{"key":"y_wgs84","value":"52.262567"},{"key":"x_wgs84","value":"20.989581"},{"key":"adres","value":"ul. LISA-KULI L"},{"key":"data_wyk_pom","value":"18991230"},{"key":"gatunek1","value":"Rosa  sp."},{"key":"gatunek","value":"róża  sp."},{"key":"wiek_w_dni","value":"0"},{"key":"jednostka","value":"Dzielnica Żoliborz"},{"key":"rank","value":"0.0706241"},{"key":"_full_count","value":"964"},{"key":"_id","value":"6355"},{"key":"dzielnica","value":"Żoliborz"},{"key":"stan_zdrowia","value":"dobry"},{"key":"miasto","value":"Warszawa"},{"key":"lokalizacja","value":"Ulica bez nazwy"},{"key":"numer_inw","value":"K13186"},{"key":"y","value":"5792113.31874126"},{"key":"x","value":"7499288.67846154"}]},{"properties":[{"key":"y_wgs84","value":"52.262565"},{"key":"x_wgs84","value":"20.989648"},{"key":"adres","value":"ul. LISA-KULI L"},{"key":"data_wyk_pom","value":"18991230"},{"key":"gatunek1","value":"Rosa  sp."},{"key":"gatunek","value":"róża  sp."},{"key":"wiek_w_dni","value":"0"},{"key":"jednostka","value":"Dzielnica Żoliborz"},{"key":"rank","value":"0.0706241"},{"key":"_full_count","value":"964"},{"key":"_id","value":"6356"},{"key":"dzielnica","value":"Żoliborz"},{"key":"stan_zdrowia","value":"dobry"},{"key":"miasto","value":"Warszawa"},{"key":"lokalizacja","value":"Ulica bez nazwy"},{"key":"numer_inw","value":"K13187"},{"key":"y","value":"5792113.08993007"},{"key":"x","value":"7499293.25594406"}]},{"properties":[{"key":"y_wgs84","value":"52.262565"},{"key":"x_wgs84","value":"20.989676"},{"key":"adres","value":"ul. LISA-KULI L"},{"key":"data_wyk_pom","value":"18991230"},{"key":"gatunek1","value":"Rosa  sp."},{"key":"gatunek","value":"róża  sp."},{"key":"wiek_w_dni","value":"0"},{"key":"jednostka","value":"Dzielnica Żoliborz"},{"key":"rank","value":"0.0706241"},{"key":"_full_count","value":"964"},{"key":"_id","value":"6357"},{"key":"dzielnica","value":"Żoliborz"},{"key":"stan_zdrowia","value":"dobry"},{"key":"miasto","value":"Warszawa"},{"key":"lokalizacja","value":"Ulica bez nazwy"},{"key":"numer_inw","value":"K13188"},{"key":"y","value":"5792113.13482517"},{"key":"x","value":"7499295.1786014"}]},{"properties":[{"key":"y_wgs84","value":"52.262562"},{"key":"x_wgs84","value":"20.9897"},{"key":"adres","value":"ul. LISA-KULI L"},{"key":"data_wyk_pom","value":"18991230"},{"key":"gatunek1","value":"Rosa  sp."},{"key":"gatunek","value":"róża  sp."},{"key":"wiek_w_dni","value":"0"},{"key":"jednostka","value":"Dzielnica Żoliborz"},{"key":"rank","value":"0.0706241"},{"key":"_full_count","value":"964"},{"key":"_id","value":"6358"},{"key":"dzielnica","value":"Żoliborz"},{"key":"stan_zdrowia","value":"dobry"},{"key":"miasto","value":"Warszawa"},{"key":"lokalizacja","value":"Ulica bez nazwy"},{"key":"numer_inw","value":"K13189"},{"key":"y","value":"5792112.81538462"},{"key":"x","value":"7499296.82713287"}]},{"properties":[{"key":"y_wgs84","value":"52.262561"},{"key":"x_wgs84","value":"20.989727"},{"key":"adres","value":"ul. LISA-KULI L"},{"key":"data_wyk_pom","value":"18991230"},{"key":"gatunek1","value":"Rosa  sp."},{"key":"gatunek","value":"róża  sp."},{"key":"wiek_w_dni","value":"0"},{"key":"jednostka","value":"Dzielnica Żoliborz"},{"key":"rank","value":"0.0706241"},{"key":"_full_count","value":"964"},{"key":"_id","value":"6359"},{"key":"dzielnica","value":"Żoliborz"},{"key":"stan_zdrowia","value":"średni"},{"key":"miasto","value":"Warszawa"},{"key":"lokalizacja","value":"Ulica bez nazwy"},{"key":"numer_inw","value":"K13190"},{"key":"y","value":"5792112.72335664"},{"key":"x","value":"7499298.65776224"}]},{"properties":[{"key":"y_wgs84","value":"52.264137"},{"key":"x_wgs84","value":"20.989837"},{"key":"adres","value":"ul. bez nazwy"},{"key":"data_wyk_pom","value":"18991230"},{"key":"gatunek1","value":"Spiraea  sp."},{"key":"gatunek","value":"tawuła  sp."},{"key":"wiek_w_dni","value":"0"},{"key":"jednostka","value":"Dzielnica Żoliborz"},{"key":"rank","value":"0.0706241"},{"key":"_full_count","value":"964"},{"key":"_id","value":"6360"},{"key":"dzielnica","value":"Żoliborz"},{"key":"stan_zdrowia","value":"średni"},{"key":"miasto","value":"Warszawa"},{"key":"lokalizacja","value":"Ulica bez nazwy"},{"key":"numer_inw","value":"K13191"},{"key":"y","value":"5792288.06699301"},{"key":"x","value":"7499306.19006993"}]},{"properties":[{"key":"y_wgs84","value":"52.263621"},{"key":"x_wgs84","value":"20.990339"},{"key":"adres","value":"ul. bez nazwy"},{"key":"data_wyk_pom","value":"18991230"},{"key":"gatunek1","value":"Sambucus nigra"},{"key":"gatunek","value":"bez czarny"},{"key":"wiek_w_dni","value":"0"},{"key":"jednostka","value":"Dzielnica Żoliborz"},{"key":"rank","value":"0.0706241"},{"key":"_full_count","value":"964"},{"key":"_id","value":"6361"},{"key":"dzielnica","value":"Żoliborz"},{"key":"stan_zdrowia","value":"dobry"},{"key":"miasto","value":"Warszawa"},{"key":"lokalizacja","value":"Ulica bez nazwy"},{"key":"numer_inw","value":"K13192"},{"key":"y","value":"5792230.66531469"},{"key":"x","value":"7499340.46979021"}]},{"properties":[{"key":"y_wgs84","value":"52.262377"},{"key":"x_wgs84","value":"20.990332"},{"key":"adres","value":"ul. CZARNIECKIEGO S"},{"key":"data_wyk_pom","value":"18991230"},{"key":"gatunek1","value":"Sambucus nigra"},{"key":"gatunek","value":"bez czarny"},{"key":"wiek_w_dni","value":"0"},{"key":"jednostka","value":"Dzielnica Żoliborz"},{"key":"rank","value":"0.0706241"},{"key":"_full_count","value":"964"},{"key":"_id","value":"6362"},{"key":"dzielnica","value":"Żoliborz"},{"key":"stan_zdrowia","value":"średni"},{"key":"miasto","value":"Warszawa"},{"key":"lokalizacja","value":"Ulica bez nazwy"},{"key":"numer_inw","value":"K13193"},{"key":"y","value":"5792092.21524476"},{"key":"x","value":"7499339.94783217"}]},{"properties":[{"key":"y_wgs84","value":"52.262475"},{"key":"x_wgs84","value":"20.989845"},{"key":"adres","value":"ul. LISA-KULI L"},{"key":"data_wyk_pom","value":"18991230"},{"key":"gatunek1","value":"Thuja  sp."},{"key":"gatunek","value":"żywotnik  sp."},{"key":"wiek_w_dni","value":"0"},{"key":"jednostka","value":"Dzielnica Żoliborz"},{"key":"rank","value":"0.0706241"},{"key":"_full_count","value":"964"},{"key":"_id","value":"6363"},{"key":"dzielnica","value":"Żoliborz"},{"key":"stan_zdrowia","value":"średni"},{"key":"miasto","value":"Warszawa"},{"key":"lokalizacja","value":"Ulica bez nazwy"},{"key":"numer_inw","value":"K13194"},{"key":"y","value":"5792103.13314685"},{"key":"x","value":"7499306.71370629"}]},{"properties":[{"key":"y_wgs84","value":"52.262474"},{"key":"x_wgs84","value":"20.989807"},{"key":"adres","value":"ul. LISA-KULI L"},{"key":"data_wyk_pom","value":"18991230"},{"key":"gatunek1","value":"Thuja  sp."},{"key":"gatunek","value":"żywotnik  sp."},{"key":"wiek_w_dni","value":"0"},{"key":"jednostka","value":"Dzielnica Żoliborz"},{"key":"rank","value":"0.0706241"},{"key":"_full_count","value":"964"},{"key":"_id","value":"6364"},{"key":"dzielnica","value":"Żoliborz"},{"key":"stan_zdrowia","value":"średni"},{"key":"miasto","value":"Warszawa"},{"key":"lokalizacja","value":"Ulica bez nazwy"},{"key":"numer_inw","value":"K13195"},{"key":"y","value":"5792103.04181818"},{"key":"x","value":"7499304.15020979"}]},{"properties":[{"key":"y_wgs84","value":"52.262478"},{"key":"x_wgs84","value":"20.989775"},{"key":"adres","value":"ul. LISA-KULI L"},{"key":"data_wyk_pom","value":"18991230"},{"key":"gatunek1","value":"Thuja  sp."},{"key":"gatunek","value":"żywotnik  sp."},{"key":"wiek_w_dni","value":"0"},{"key":"jednostka","value":"Dzielnica Żoliborz"},{"key":"rank","value":"0.0706241"},{"key":"_full_count","value":"964"},{"key":"_id","value":"6365"},{"key":"dzielnica","value":"Żoliborz"},{"key":"stan_zdrowia","value":"średni"},{"key":"miasto","value":"Warszawa"},{"key":"lokalizacja","value":"Ulica bez nazwy"},{"key":"numer_inw","value":"K13196"},{"key":"y","value":"5792103.49902098"},{"key":"x","value":"7499301.90685315"}]},{"properties":[{"key":"y_wgs84","value":"52.262481"},{"key":"x_wgs84","value":"20.989744"},{"key":"adres","value":"ul. LISA-KULI L"},{"key":"data_wyk_pom","value":"18991230"},{"key":"gatunek1","value":"Thuja  sp."},{"key":"gatunek","value":"żywotnik  sp."},{"key":"wiek_w_dni","value":"0"},{"key":"jednostka","value":"Dzielnica Żoliborz"},{"key":"rank","value":"0.0706241"},{"key":"_full_count","value":"964"},{"key":"_id","value":"6366"},{"key":"dzielnica","value":"Żoliborz"},{"key":"stan_zdrowia","value":"średni"},{"key":"miasto","value":"Warszawa"},{"key":"lokalizacja","value":"Ulica bez nazwy"},{"key":"numer_inw","value":"K13197"},{"key":"y","value":"5792103.81874126"},{"key":"x","value":"7499299.8013986"}]},{"properties":[{"key":"y_wgs84","value":"52.26261"},{"key":"x_wgs84","value":"20.987723"},{"key":"adres","value":"ul. FELIŃSKIEGO A"},{"key":"data_wyk_pom","value":"18991230"},{"key":"gatunek1","value":"Symphoricarpos albus"},{"key":"gatunek","value":"śnieguliczka biała"},{"key":"wiek_w_dni","value":"0"},{"key":"jednostka","value":"Dzielnica Żoliborz"},{"key":"rank","value":"0.0706241"},{"key":"_full_count","value":"964"},{"key":"_id","value":"6367"},{"key":"dzielnica","value":"Żoliborz"},{"key":"stan_zdrowia","value":"dobry"},{"key":"miasto","value":"Warszawa"},{"key":"lokalizacja","value":"Ulica bez nazwy"},{"key":"numer_inw","value":"K13198"},{"key":"y","value":"5792118.13342657"},{"key":"x","value":"7499161.87216783"}]},{"properties":[{"key":"y_wgs84","value":"52.265128"},{"key":"x_wgs84","value":"20.986093"},{"key":"adres","value":"ul. FELIŃSKIEGO A"},{"key":"data_wyk_pom","value":"18991230"},{"key":"gatunek1","value":"Ligustrum vulgare"},{"key":"gatunek","value":"ligustr pospolity"},{"key":"wiek_w_dni","value":"0"},{"key":"jednostka","value":"Dzielnica Żoliborz"},{"key":"rank","value":"0.0706241"},{"key":"_full_count","value":"964"},{"key":"_id","value":"6368"},{"key":"dzielnica","value":"Żoliborz"},{"key":"stan_zdrowia","value":"średni"},{"key":"miasto","value":"Warszawa"},{"key":"lokalizacja","value":"Ulica bez nazwy"},{"key":"numer_inw","value":"K13199"},{"key":"y","value":"5792398.33636364"},{"key":"x","value":"7499050.59216783"}]},{"properties":[{"key":"y_wgs84","value":"52.266389"},{"key":"x_wgs84","value":"20.962986"},{"key":"adres","value":"ul. BRONIEWSKIEGO W"},{"key":"data_wyk_pom","value":"18991230"},{"key":"gatunek1","value":"Cotinus coggygria"},{"key":"gatunek","value":"perukowiec podolski"},{"key":"wiek_w_dni","value":"0"},{"key":"jednostka","value":"Dzielnica Żoliborz"},{"key":"rank","value":"0.0706241"},{"key":"_full_count","value":"964"},{"key":"_id","value":"6369"},{"key":"dzielnica","value":"Żoliborz"},{"key":"stan_zdrowia","value":"średni"},{"key":"miasto","value":"Warszawa"},{"key":"lokalizacja","value":"Ulica bez nazwy"},{"key":"numer_inw","value":"K13200"},{"key":"y","value":"5792539.24993007"},{"key":"x","value":"7497473.26447552"}]},{"properties":[{"key":"y_wgs84","value":"52.262285"},{"key":"x_wgs84","value":"20.978495"},{"key":"adres","value":"ul. MATYSIAKÓWNY K"},{"key":"data_wyk_pom","value":"18991230"},{"key":"gatunek1","value":"Sambucus nigra"},{"key":"gatunek","value":"bez czarny"},{"key":"wiek_w_dni","value":"0"},{"key":"jednostka","value":"Dzielnica Żoliborz"},{"key":"rank","value":"0.0706241"},{"key":"_full_count","value":"964"},{"key":"_id","value":"6370"},{"key":"dzielnica","value":"Żoliborz"},{"key":"stan_zdrowia","value":"dobry"},{"key":"miasto","value":"Warszawa"},{"key":"lokalizacja","value":"Ulica bez nazwy"},{"key":"numer_inw","value":"K13201"},{"key":"y","value":"5792082.11426573"},{"key":"x","value":"7498531.80881119"}]},{"properties":[{"key":"y_wgs84","value":"52.26227"},{"key":"x_wgs84","value":"20.978578"},{"key":"adres","value":"ul. MATYSIAKÓWNY K"},{"key":"data_wyk_pom","value":"18991230"},{"key":"gatunek1","value":"Sambucus nigra"},{"key":"gatunek","value":"bez czarny"},{"key":"wiek_w_dni","value":"0"},{"key":"jednostka","value":"Dzielnica Żoliborz"},{"key":"rank","value":"0.0706241"},{"key":"_full_count","value":"964"},{"key":"_id","value":"6371"},{"key":"dzielnica","value":"Żoliborz"},{"key":"stan_zdrowia","value":"dobry"},{"key":"miasto","value":"Warszawa"},{"key":"lokalizacja","value":"Ulica bez nazwy"},{"key":"numer_inw","value":"K13202"},{"key":"y","value":"5792080.46881119"},{"key":"x","value":"7498537.4848951"}]},{"properties":[{"key":"y_wgs84","value":"52.262212"},{"key":"x_wgs84","value":"20.978548"},{"key":"adres","value":"ul. MATYSIAKÓWNY K"},{"key":"data_wyk_pom","value":"18991230"},{"key":"gatunek1","value":"Sambucus nigra"},{"key":"gatunek","value":"bez czarny"},{"key":"wiek_w_dni","value":"0"},{"key":"jednostka","value":"Dzielnica Żoliborz"},{"key":"rank","value":"0.0706241"},{"key":"_full_count","value":"964"},{"key":"_id","value":"6372"},{"key":"dzielnica","value":"Żoliborz"},{"key":"stan_zdrowia","value":"dobry"},{"key":"miasto","value":"Warszawa"},{"key":"lokalizacja","value":"Ulica bez nazwy"},{"key":"numer_inw","value":"K13203"},{"key":"y","value":"5792073.9848951"},{"key":"x","value":"7498535.46895105"}]},{"properties":[{"key":"y_wgs84","value":"52.263213"},{"key":"x_wgs84","value":"20.982676"},{"key":"adres","value":"ul. bez nazwy"},{"key":"data_wyk_pom","value":"18991230"},{"key":"gatunek1","value":"Sambucus nigra"},{"key":"gatunek","value":"bez czarny"},{"key":"wiek_w_dni","value":"0"},{"key":"jednostka","value":"Dzielnica Żoliborz"},{"key":"rank","value":"0.0706241"},{"key":"_full_count","value":"964"},{"key":"_id","value":"6373"},{"key":"dzielnica","value":"Żoliborz"},{"key":"stan_zdrowia","value":"dobry"},{"key":"miasto","value":"Warszawa"},{"key":"lokalizacja","value":"Ulica bez nazwy"},{"key":"numer_inw","value":"K13204"},{"key":"y","value":"5792185.32797203"},{"key":"x","value":"7498817.31188811"}]},{"properties":[{"key":"y_wgs84","value":"52.263747"},{"key":"x_wgs84","value":"20.988401"},{"key":"adres","value":"ul. bez nazwy"},{"key":"data_wyk_pom","value":"18991230"},{"key":"gatunek1","value":"Sambucus nigra"},{"key":"gatunek","value":"bez czarny"},{"key":"wiek_w_dni","value":"0"},{"key":"jednostka","value":"Dzielnica Żoliborz"},{"key":"rank","value":"0.0706241"},{"key":"_full_count","value":"964"},{"key":"_id","value":"6374"},{"key":"dzielnica","value":"Żoliborz"},{"key":"stan_zdrowia","value":"średni"},{"key":"miasto","value":"Warszawa"},{"key":"lokalizacja","value":"Ulica bez nazwy"},{"key":"numer_inw","value":"K13205"},{"key":"y","value":"5792244.70293706"},{"key":"x","value":"7499208.17440559"}]},{"properties":[{"key":"y_wgs84","value":"52.263641"},{"key":"x_wgs84","value":"20.98064"},{"key":"adres","value":"ul. WYSPIAŃSKIEGO S"},{"key":"data_wyk_pom","value":"18991230"},{"key":"gatunek1","value":"Ribes  sp. (porzeczka)"},{"key":"gatunek","value":"porzeczka  sp."},{"key":"wiek_w_dni","value":"0"},{"key":"jednostka","value":"Dzielnica Żoliborz"},{"key":"rank","value":"0.0706241"},{"key":"_full_count","value":"964"},{"key":"_id","value":"6375"},{"key":"dzielnica","value":"Żoliborz"},{"key":"stan_zdrowia","value":"dobry"},{"key":"miasto","value":"Warszawa"},{"key":"lokalizacja","value":"Ulica bez nazwy"},{"key":"numer_inw","value":"K13206"},{"key":"y","value":"5792233.03496503"},{"key":"x","value":"7498678.34223776"}]},{"properties":[{"key":"y_wgs84","value":"52.264401"},{"key":"x_wgs84","value":"20.984529"},{"key":"adres","value":"ul. KOZIETULSKIEGO J"},{"key":"data_wyk_pom","value":"18991230"},{"key":"gatunek1","value":"Rhus typhina"},{"key":"gatunek","value":"sumak octowiec"},{"key":"wiek_w_dni","value":"0"},{"key":"jednostka","value":"Dzielnica Żoliborz"},{"key":"rank","value":"0.0706241"},{"key":"_full_count","value":"964"},{"key":"_id","value":"6376"},{"key":"dzielnica","value":"Żoliborz"},{"key":"stan_zdrowia","value":"średni"},{"key":"miasto","value":"Warszawa"},{"key":"lokalizacja","value":"Ulica bez nazwy"},{"key":"numer_inw","value":"K13207"},{"key":"y","value":"5792317.44629371"},{"key":"x","value":"7498943.82461538"}]},{"properties":[{"key":"y_wgs84","value":"52.264253"},{"key":"x_wgs84","value":"20.984316"},{"key":"adres","value":"ul. KOZIETULSKIEGO J"},{"key":"data_wyk_pom","value":"18991230"},{"key":"gatunek1","value":"Forsythia  sp."},{"key":"gatunek","value":"forsycja  sp."},{"key":"wiek_w_dni","value":"0"},{"key":"jednostka","value":"Dzielnica Żoliborz"},{"key":"rank","value":"0.0706241"},{"key":"_full_count","value":"964"},{"key":"_id","value":"6377"},{"key":"dzielnica","value":"Żoliborz"},{"key":"stan_zdrowia","value":"średni"},{"key":"miasto","value":"Warszawa"},{"key":"lokalizacja","value":"Ulica bez nazwy"},{"key":"numer_inw","value":"K13208"},{"key":"y","value":"5792301.01076923"},{"key":"x","value":"7498929.2641958"}]},{"properties":[{"key":"y_wgs84","value":"52.264914"},{"key":"x_wgs84","value":"20.984265"},{"key":"adres","value":"ul. KOZIETULSKIEGO J"},{"key":"data_wyk_pom","value":"18991230"},{"key":"gatunek1","value":"Taxus baccata 'Repandens'"},{"key":"gatunek","value":"cis pospolity \"Repandens\""},{"key":"wiek_w_dni","value":"0"},{"key":"jednostka","value":"Dzielnica Żoliborz"},{"key":"rank","value":"0.0706241"},{"key":"_full_count","value":"964"},{"key":"_id","value":"6378"},{"key":"dzielnica","value":"Żoliborz"},{"key":"stan_zdrowia","value":"dobry"},{"key":"miasto","value":"Warszawa"},{"key":"lokalizacja","value":"Ulica bez nazwy"},{"key":"numer_inw","value":"K13209"},{"key":"y","value":"5792374.61804196"},{"key":"x","value":"7498925.80111888"}]},{"properties":[{"key":"y_wgs84","value":"52.2651"},{"key":"x_wgs84","value":"20.984189"},{"key":"adres","value":"ul. KOZIETULSKIEGO J"},{"key":"data_wyk_pom","value":"18991230"},{"key":"gatunek1","value":"Thuja  sp."},{"key":"gatunek","value":"żywotnik  sp."},{"key":"wiek_w_dni","value":"0"},{"key":"jednostka","value":"Dzielnica Żoliborz"},{"key":"rank","value":"0.0706241"},{"key":"_full_count","value":"964"},{"key":"_id","value":"6379"},{"key":"dzielnica","value":"Żoliborz"},{"key":"stan_zdrowia","value":"dobry"},{"key":"miasto","value":"Warszawa"},{"key":"lokalizacja","value":"Ulica bez nazwy"},{"key":"numer_inw","value":"K13210"},{"key":"y","value":"5792395.21216783"},{"key":"x","value":"7498920.63286713"}]},{"properties":[{"key":"y_wgs84","value":"52.265341"},{"key":"x_wgs84","value":"20.984161"},{"key":"adres","value":"ul. KOZIETULSKIEGO J"},{"key":"data_wyk_pom","value":"18991230"},{"key":"gatunek1","value":"Forsythia  sp."},{"key":"gatunek","value":"forsycja  sp."},{"key":"wiek_w_dni","value":"0"},{"key":"jednostka","value":"Dzielnica Żoliborz"},{"key":"rank","value":"0.0706241"},{"key":"_full_count","value":"964"},{"key":"_id","value":"6380"},{"key":"dzielnica","value":"Żoliborz"},{"key":"stan_zdrowia","value":"dobry"},{"key":"miasto","value":"Warszawa"},{"key":"lokalizacja","value":"Ulica bez nazwy"},{"key":"numer_inw","value":"K13211"},{"key":"y","value":"5792422.10657343"},{"key":"x","value":"7498918.71622378"}]},{"properties":[{"key":"y_wgs84","value":"52.266082"},{"key":"x_wgs84","value":"20.988559"},{"key":"adres","value":"ul. MIEROSŁAWSKIEGO L"},{"key":"data_wyk_pom","value":"18991230"},{"key":"gatunek1","value":"Syringa vulgaris"},{"key":"gatunek","value":"lilak pospolity"},{"key":"wiek_w_dni","value":"0"},{"key":"jednostka","value":"Dzielnica Żoliborz"},{"key":"rank","value":"0.0706241"},{"key":"_full_count","value":"964"},{"key":"_id","value":"6452"},{"key":"dzielnica","value":"Żoliborz"},{"key":"stan_zdrowia","value":"dobry"},{"key":"miasto","value":"Warszawa"},{"key":"lokalizacja","value":"Ulica bez nazwy"},{"key":"numer_inw","value":"K12685"},{"key":"y","value":"5792504.46671329"},{"key":"x","value":"7499218.97328671"}]},{"properties":[{"key":"y_wgs84","value":"52.266047"},{"key":"x_wgs84","value":"20.988521"},{"key":"adres","value":"ul. MIEROSŁAWSKIEGO L"},{"key":"data_wyk_pom","value":"18991230"},{"key":"gatunek1","value":"Philadelphus coronarius"},{"key":"gatunek","value":"jaśminowiec wonny"},{"key":"wiek_w_dni","value":"0"},{"key":"jednostka","value":"Dzielnica Żoliborz"},{"key":"rank","value":"0.0706241"},{"key":"_full_count","value":"964"},{"key":"_id","value":"6453"},{"key":"dzielnica","value":"Żoliborz"},{"key":"stan_zdrowia","value":"dobry"},{"key":"miasto","value":"Warszawa"},{"key":"lokalizacja","value":"Ulica bez nazwy"},{"key":"numer_inw","value":"K12686"},{"key":"y","value":"5792500.5406993"},{"key":"x","value":"7499216.36335664"}]},{"properties":[{"key":"y_wgs84","value":"52.265585"},{"key":"x_wgs84","value":"20.988959"},{"key":"adres","value":"ul. MICKIEWICZA A"},{"key":"data_wyk_pom","value":"18991230"},{"key":"gatunek1","value":"Cornus alba"},{"key":"gatunek","value":"dereń biały"},{"key":"wiek_w_dni","value":"0"},{"key":"jednostka","value":"Dzielnica Żoliborz"},{"key":"rank","value":"0.0706241"},{"key":"_full_count","value":"964"},{"key":"_id","value":"6454"},{"key":"dzielnica","value":"Żoliborz"},{"key":"stan_zdrowia","value":"średni"},{"key":"miasto","value":"Warszawa"},{"key":"lokalizacja","value":"Ulica bez nazwy"},{"key":"numer_inw","value":"K12689"},{"key":"y","value":"5792449.12265734"},{"key":"x","value":"7499246.29244755"}]},{"properties":[{"key":"y_wgs84","value":"52.265485"},{"key":"x_wgs84","value":"20.989077"},{"key":"adres","value":"ul. MICKIEWICZA A"},{"key":"data_wyk_pom","value":"18991230"},{"key":"gatunek1","value":"Syringa vulgaris"},{"key":"gatunek","value":"lilak pospolity"},{"key":"wiek_w_dni","value":"0"},{"key":"jednostka","value":"Dzielnica Żoliborz"},{"key":"rank","value":"0.0706241"},{"key":"_full_count","value":"964"},{"key":"_id","value":"6455"},{"key":"dzielnica","value":"Żoliborz"},{"key":"stan_zdrowia","value":"dobry"},{"key":"miasto","value":"Warszawa"},{"key":"lokalizacja","value":"Ulica bez nazwy"},{"key":"numer_inw","value":"K12690"},{"key":"y","value":"5792438.02587413"},{"key":"x","value":"7499254.34741259"}]},{"properties":[{"key":"y_wgs84","value":"52.265468"},{"key":"x_wgs84","value":"20.989055"},{"key":"adres","value":"ul. MICKIEWICZA A"},{"key":"data_wyk_pom","value":"18991230"},{"key":"gatunek1","value":"Syringa vulgaris"},{"key":"gatunek","value":"lilak pospolity"},{"key":"wiek_w_dni","value":"0"},{"key":"jednostka","value":"Dzielnica Żoliborz"},{"key":"rank","value":"0.0706241"},{"key":"_full_count","value":"964"},{"key":"_id","value":"6456"},{"key":"dzielnica","value":"Żoliborz"},{"key":"stan_zdrowia","value":"dobry"},{"key":"miasto","value":"Warszawa"},{"key":"lokalizacja","value":"Ulica bez nazwy"},{"key":"numer_inw","value":"K12691"},{"key":"y","value":"5792436.15426573"},{"key":"x","value":"7499252.83678322"}]},{"properties":[{"key":"y_wgs84","value":"52.265459"},{"key":"x_wgs84","value":"20.989091"},{"key":"adres","value":"ul. MICKIEWICZA A"},{"key":"data_wyk_pom","value":"18991230"},{"key":"gatunek1","value":"Syringa vulgaris"},{"key":"gatunek","value":"lilak pospolity"},{"key":"wiek_w_dni","value":"0"},{"key":"jednostka","value":"Dzielnica Żoliborz"},{"key":"rank","value":"0.0706241"},{"key":"_full_count","value":"964"},{"key":"_id","value":"6457"},{"key":"dzielnica","value":"Żoliborz"},{"key":"stan_zdrowia","value":"dobry"},{"key":"miasto","value":"Warszawa"},{"key":"lokalizacja","value":"Ulica bez nazwy"},{"key":"numer_inw","value":"K12692"},{"key":"y","value":"5792435.10363636"},{"key":"x","value":"7499255.26265734"}]},{"properties":[{"key":"y_wgs84","value":"52.26376"},{"key":"x_wgs84","value":"20.983211"},{"key":"adres","value":"ul. WIENIAWSKIEGO H"},{"key":"data_wyk_pom","value":"18991230"},{"key":"gatunek1","value":"Rosa canina"},{"key":"gatunek","value":"róża dzika"},{"key":"wiek_w_dni","value":"0"},{"key":"jednostka","value":"Dzielnica Żoliborz"},{"key":"rank","value":"0.0706241"},{"key":"_full_count","value":"964"},{"key":"_id","value":"6502"},{"key":"dzielnica","value":"Żoliborz"},{"key":"stan_zdrowia","value":"dobry"},{"key":"miasto","value":"Warszawa"},{"key":"lokalizacja","value":"Ulica bez nazwy"},{"key":"numer_inw","value":"K13230"},{"key":"y","value":"5792246.18783217"},{"key":"x","value":"7498853.85678322"}]},{"properties":[{"key":"y_wgs84","value":"52.265441"},{"key":"x_wgs84","value":"20.989067"},{"key":"adres","value":"ul. MICKIEWICZA A"},{"key":"data_wyk_pom","value":"18991230"},{"key":"gatunek1","value":"Philadelphus coronarius"},{"key":"gatunek","value":"jaśminowiec wonny"},{"key":"wiek_w_dni","value":"0"},{"key":"jednostka","value":"Dzielnica Żoliborz"},{"key":"rank","value":"0.0706241"},{"key":"_full_count","value":"964"},{"key":"_id","value":"6458"},{"key":"dzielnica","value":"Żoliborz"},{"key":"stan_zdrowia","value":"dobry"},{"key":"miasto","value":"Warszawa"},{"key":"lokalizacja","value":"Ulica bez nazwy"},{"key":"numer_inw","value":"K12693"},{"key":"y","value":"5792433.18629371"},{"key":"x","value":"7499253.65986014"}]}],"limit":"0","total":"964"}